responses/__init__.py
responses/_recorder.py
responses/matchers.py
responses/py.typed
responses/registries.py
responses-0.25.6.dist-info/LICENSE
responses-0.25.6.dist-info/METADATA
responses-0.25.6.dist-info/WHEEL
responses-0.25.6.dist-info/top_level.txt
responses-0.25.6.dist-info/RECORD
