Metadata-Version: 2.1
Name: responses
Version: 0.25.6
Summary: A utility library for mocking out the `requests` Python library.
Home-page: https://github.com/getsentry/responses
Author: David Cramer
License: Apache 2.0
Project-URL: Bug Tracker, https://github.com/getsentry/responses/issues
Project-URL: Changes, https://github.com/getsentry/responses/blob/master/CHANGES
Project-URL: Documentation, https://github.com/getsentry/responses/blob/master/README.rst
Project-URL: Source Code, https://github.com/getsentry/responses
Platform: UNKNOWN
Classifier: Intended Audience :: Developers
Classifier: Intended Audience :: System Administrators
Classifier: Operating System :: OS Independent
Classifier: Programming Language :: Python
Classifier: Programming Language :: Python :: 3
Classifier: Programming Language :: Python :: 3.8
Classifier: Programming Language :: Python :: 3.9
Classifier: Programming Language :: Python :: 3.10
Classifier: Programming Language :: Python :: 3.11
Classifier: Programming Language :: Python :: 3.12
Classifier: Topic :: Software Development
Requires-Python: >=3.8
Provides-Extra: tests
License-File: LICENSE
